Metadata-Version: 2.1
Name: pymeetings
Version: 0.0.1
Summary: UNKNOWN
Home-page: https://github.com/fregocap/PyMeeting
Author: Fabio Capela
Author-email: capela625@gmail.com
License: UNKNOWN
Platform: UNKNOWN
Classifier: Programming Language :: Python :: 3
Classifier: License :: OSI Approved :: MIT License
Classifier: Operating System :: OS Independent
Requires-Python: >=3.6
